isv/__init__.py
isv/alternative.py
isv/annotate.py
isv/config.py
isv/isv.py
isv/predict.py
isv/shap_vals.py
isv/data/train_gain.tsv.gz
isv/data/train_loss.tsv.gz
isv/data/validation_gain.tsv.gz
isv/data/validation_loss.tsv.gz
isv/data/preprocessed/gencode_genes.json.gz
isv/data/preprocessed/hi_genes.json.gz
isv/data/preprocessed/hits_regions.json.gz
isv/data/preprocessed/regulatory.json.gz
isv/models/ISV_gain.json
isv/models/ISV_loss.json
isv/scripts/__init__.py
isv/scripts/constants.py
isv/scripts/helpers.py
isv/scripts/open_model.py
isv/scripts/prepare_df.py
isv-0.3.16.dist-info/METADATA
isv-0.3.16.dist-info/WHEEL
isv-0.3.16.dist-info/top_level.txt
isv-0.3.16.dist-info/RECORD
