Metadata-Version: 2.1
Name: isv
Version: 0.3.16
Summary: Automated Interpretation of Structural Copy Number Variants
Home-page: https://github.com/tsladecek/isv_package
Author: Tomas Sladecek
Author-email: tomas.sladecek@geneton.sk
Maintainer: Tomas Sladecek
Keywords: python,machine learning,copy number variation
Classifier: Development Status :: 3 - Alpha
Classifier: Intended Audience :: Developers
Classifier: License :: Free for non-commercial use
Classifier: Programming Language :: Python :: 3
Classifier: Programming Language :: Python :: 3.6
Classifier: Programming Language :: Python :: 3.7
Classifier: Programming Language :: Python :: 3.8
Classifier: Programming Language :: Python :: 3.9
Classifier: Programming Language :: Python :: 3 :: Only
Requires-Python: >=3.6, <4
Requires-Dist: numpy (<2,>=1.22.0)
Requires-Dist: xgboost (<2,>=1.4.0)
Requires-Dist: pandas (<2,>=1.2.0)
Requires-Dist: shap (>=0.39.0)
Requires-Dist: sklearn-json (>=0.1.0)
Requires-Dist: numba (>=0.53.0)
Requires-Dist: plotly (<6,>5)
